backtraderbd/__init__.py
backtraderbd/btask.py
backtraderbd/tasks.py
backtraderbd/data/__init__.py
backtraderbd/data/bdshare.py
backtraderbd/data/utils.py
backtraderbd/libs/__init__.py
backtraderbd/libs/log.py
backtraderbd/libs/models.py
backtraderbd/settings/__init__.py
backtraderbd/settings/common.py
backtraderbd/settings/dev.py
backtraderbd/settings/prod.py
backtraderbd/settings/test.py
backtraderbd/strategies/__init__.py
backtraderbd/strategies/base.py
backtraderbd/strategies/emac.py
backtraderbd/strategies/macd.py
backtraderbd/strategies/rsi.py
backtraderbd/strategies/smac.py
backtraderbd/strategies/utils.py
backtraderbd-0.1.0.dist-info/LICENSE
backtraderbd-0.1.0.dist-info/METADATA
backtraderbd-0.1.0.dist-info/WHEEL
backtraderbd-0.1.0.dist-info/top_level.txt
backtraderbd-0.1.0.dist-info/RECORD
