Metadata-Version: 2.1
Name: backtraderbd
Version: 0.1.0
Summary: A backtrader utility
Home-page: https://github.com/rochi88/backtraderbd
Author: Raisul Islam
Author-email: raisul.exe@gmail.com
License: MIT
Download-URL: https://github.com/rochi88/backtraderbd/archive/master.zip
Keywords: backtrader,backtester
Platform: UNKNOWN
Classifier: Development Status :: 3 - Alpha
Classifier: Intended Audience :: Developers
Classifier: License :: OSI Approved :: MIT License
Classifier: Operating System :: OS Independent
Classifier: Programming Language :: Python
Classifier: Programming Language :: Python :: 3
Classifier: Programming Language :: Python :: 3.5
Classifier: Programming Language :: Python :: 3.6
Classifier: Programming Language :: Python :: 3.7
Classifier: Programming Language :: Python :: 3.8
Classifier: Topic :: Software Development :: Libraries :: Python Modules
Classifier: Topic :: Scientific/Engineering :: Artificial Intelligence
Classifier: Topic :: Scientific/Engineering :: Information Analysis
Classifier: Topic :: Office/Business :: Financial :: Investment
Requires-Python: >=3.5
Requires-Dist: beautifulsoup4
Requires-Dist: requests
Requires-Dist: pandas
Requires-Dist: backtrader
Requires-Dist: bdshare
Requires-Dist: arctic
Requires-Dist: proviso
